client/__init__.py
client/httpClient.py
parse/__init__.py
parse/parseCsv.py
parse/parseError.py
parse/queryParams.py
parse/run.py
sftp-client/__init__.py
sftp-client/httpClient.py
sftp-parse/__init__.py
sftp-parse/parseCsv.py
sftp-parse/parseError.py
sftp-parse/queryParams.py
sftp-test/__init__.py
sftp-test/run.py
sftp_client/__init__.py
sftp_client/httpClient.py
sftp_client/s3Client.py
sftp_parse/__init__.py
sftp_parse/parseCsv.py
sftp_parse/parseError.py
sftp_parse/queryParams.py
sftp_test/__init__.py
sftp_test/run.py
test/__init__.py
test/run.py
twilio_messaging_sftp-0.0.17.dist-info/LICENSE
twilio_messaging_sftp-0.0.17.dist-info/METADATA
twilio_messaging_sftp-0.0.17.dist-info/WHEEL
twilio_messaging_sftp-0.0.17.dist-info/top_level.txt
twilio_messaging_sftp-0.0.17.dist-info/RECORD
