Metadata-Version: 2.1
Name: twilio-messaging-sftp
Version: 0.0.17
Summary: Library for sending bulk sms/mms messages via sftp
Home-page: https://code.hq.twilio.com/messaging/messaging-sftp-lib
Author: messaging sftp
Author-email: ebogod@twilio.com
License: UNKNOWN
Platform: UNKNOWN
Classifier: Programming Language :: Python :: 3
Classifier: License :: OSI Approved :: MIT License
Classifier: Operating System :: OS Independent
Requires-Dist: twilio (==6.19.2)
Requires-Dist: boto3 (==1.9.35)
